ase/__init__.py
ase/protocol.py
ase/adapters/__init__.py
ase/adapters/autogpt.py
ase/adapters/base.py
ase/adapters/langchain.py
ase/core/__init__.py
ase/core/audit.py
ase/core/disputes.py
ase/core/extensions.py
ase/core/models.py
ase/core/serialization.py
ase/core/settlement.py
ase/core/validation.py
ase/core/versioning.py
ase/crypto/__init__.py
ase/crypto/keys.py
ase/crypto/signing.py
ase/crypto/tokens.py
ase/governance/__init__.py
ase/governance/compliance.py
ase/governance/rfc_process.py
ase/governance/steering.py
ase_protocol-1.0.8.dist-info/licenses/LICENSE
ase_protocol-1.0.8.dist-info/METADATA
ase_protocol-1.0.8.dist-info/WHEEL
ase_protocol-1.0.8.dist-info/top_level.txt
ase_protocol-1.0.8.dist-info/RECORD
