Metadata-Version: 2.4
Name: ase-protocol
Version: 1.0.8
Summary: Agent Settlement Extension (ASE) Protocol
Author-email: Garudex Labs Team <support@garudexlabs.com>
Classifier: Development Status :: 4 - Beta
Classifier: Intended Audience :: Developers
Classifier: License :: OSI Approved :: Apache Software License
Classifier: Programming Language :: Python :: 3
Requires-Python: >=3.8
License-File: LICENSE
Requires-Dist: pydantic>=2.0.0
Requires-Dist: cryptography<46,>=41.0.0
Requires-Dist: pyjwt>=2.8.0
Provides-Extra: test
Requires-Dist: pytest>=8.0.0; extra == "test"
Requires-Dist: hypothesis>=6.100.0; extra == "test"
Dynamic: license-file
